pppoe_pass/__init__.py
pppoe_pass-0.0.5.dist-info/LICENCE.txt
pppoe_pass-0.0.5.dist-info/METADATA
pppoe_pass-0.0.5.dist-info/WHEEL
pppoe_pass-0.0.5.dist-info/top_level.txt
pppoe_pass-0.0.5.dist-info/RECORD
