Metadata-Version: 2.1
Name: pppoe-pass
Version: 0.0.5
Summary: Router_pppoe
Home-page: UNKNOWN
Author: Nair
Author-email: UNKNOWN
License: MIT
Keywords: calculator
Platform: UNKNOWN
Classifier: Development Status :: 5 - Production/Stable
Classifier: Intended Audience :: Education
Classifier: Operating System :: Microsoft :: Windows :: Windows 10
Classifier: License :: OSI Approved :: MIT License
Classifier: Programming Language :: Python :: 3
Requires-Dist: beautifulsoup4
